rdlaiye/__init__.py
rdlaiye/api.py
rdlaiye/bb.py
rdlaiye/gl.py
rdlaiye/laiye_config.py
rdlaiye/rdo.py
rdlaiye/tree.py
rdlaiye-1.0.7.dist-info/LICENSE
rdlaiye-1.0.7.dist-info/METADATA
rdlaiye-1.0.7.dist-info/WHEEL
rdlaiye-1.0.7.dist-info/top_level.txt
rdlaiye-1.0.7.dist-info/RECORD
