Metadata-Version: 2.1
Name: rdlaiye
Version: 1.0.7
Summary: api sdk 
Home-page: http://www.reshapedata.com
Author: Reshapedata
Author-email: hulilei@takewiki.com.cn
License: Apache License
Keywords: reshapedata,takewiki
Platform: UNKNOWN
Requires-Python: >=3.6
Requires-Dist: requests
